{
  "general": {
    "ezPAARSE-version": "ezpaarse 3.9.2",
    "Job-ID": "c9647b70-8480-11ee-bb32-0bf4b1458acc",
    "Job-Date": "2023-11-16T14:05:16+01:00",
    "Job-Done": true,
    "result-file-ecs": "http://localhost:59599/c9647b70-8480-11ee-bb32-0bf4b1458acc",
    "predefined-settings": false,
    "URL-Traces": "http://localhost:59599/c9647b70-8480-11ee-bb32-0bf4b1458acc/job-traces.log",
    "URL-Report": "http://localhost:59599/c9647b70-8480-11ee-bb32-0bf4b1458acc/job-report.json",
    "nb-ecs": 1143,
    "nb-denied-ecs": 0,
    "nb-lines-input": 48450,
    "Rejection-Rate": "95.55 %",
    "Job-Duration": "23 s ",
    "process-speed": "2100 lignes/s",
    "client-user-agent": "axios/1.5.1",
    "ecs-speed": "49 ec/s",
    "git-branch": "HEAD",
    "git-tag": "3.9.2",
    "git-last-commit": "37e2aee2c8b8c87b53fe581233186a19cea2a3a7",
    "git-date": "2023-09-25",
    "input-format-proxy": "ezproxy",
    "input-format-literal": "%h %l %u %t \"%r\" %s %b",
    "input-format-regex": "/^([a-zA-Z0-9.\\-:]+(?:, ?[a-zA-Z0-9.\\-:]+)*) ([a-zA-Z0-9\\-]+) ([a-zA-Z0-9@.\\-_%,=]+) \\[([^\\]]+)\\] \"[A-Z]+ ([^ ]+) [^ ]+\" ([0-9]+) ([0-9]+)$/",
    "middlewares-version": "1df4e1f",
    "middlewares-date": "2023-07-26",
    "platforms-version": "70ae7649",
    "platforms-date": "2023-09-22",
    "middlewares": "filter, parser, deduplicator, istex, crossref, sudoc, hal, enhancer, geolocalizer, cut, on-campus-counter, qualifier, anonymizer",
    "crossref-queries": 3,
    "crossref-fails": 0,
    "crossref-invalid-dois": 0,
    "crossref-min-response-time": 4468,
    "crossref-max-response-time": 4809,
    "geolocalization": "",
    "on-campus-accesses": 0,
    "off-campus-accesses": 1282,
    "url-denied-ecs": "http://localhost:59599/c9647b70-8480-11ee-bb32-0bf4b1458acc/denied-ecs.csv",
    "input-first-line": "193.240.184.99 - - [25/Oct/2023:00:03:38 -0400] \"GET https://udcpp.idm.oclc.org:8443/public/admin.htm HTTP/1.1\" 200 0"
  },
  "rejets": {
    "nb-lines-ignored": 22208,
    "nb-lines-duplicate-ecs": 51,
    "nb-lines-ignored-domains": 17,
    "nb-lines-unknown-domains": 2850,
    "nb-lines-unknown-formats": 7,
    "nb-lines-unqualified-ecs": 22165,
    "nb-lines-unordered-ecs": 0,
    "nb-lines-ignored-hosts": 0,
    "nb-lines-robots-ecs": 9,
    "nb-lines-unknown-errors": 0
  },
  "stats": {
    "platforms": 15,
    "mime-PDF": 631,
    "mime-HTML": 504,
    "platform-europresse": 651,
    "rtype-ARTICLE": 686,
    "platform-dalloz": 167,
    "platform-ebscohost": 54,
    "rtype-TOC": 90,
    "platform-strada": 2,
    "rtype-SEARCH": 63,
    "platform-lextenso": 56,
    "platform-cairn": 137,
    "platform-lamyline": 24,
    "platform-britannica": 1,
    "rtype-ENCYCLOPAEDIA_ENTRY": 9,
    "platform-universalis": 8,
    "rtype-BOOK_SECTION": 101,
    "rtype-JURISPRUDENCE": 7,
    "rtype-RECORD_VIEW": 19,
    "platform-oeb": 12,
    "rtype-BOOK": 1,
    "platform-npg": 4,
    "mime-MISC": 8,
    "platform-sd": 7,
    "platform-efl": 1,
    "platform-dalloz-revues": 14,
    "platform-elnet": 5
  },
  "alerts": {
    "active-alerts": "unknown-domains"
  },
  "dedoublonnage": {
    "activated": true,
    "strategy": "CLI",
    "fieldname-C": "session",
    "fieldname-L": "login",
    "fieldname-I": "host",
    "window-misc": 30,
    "window-html": 10,
    "window-pdf": 30
  },
  "first_event": {
    "host": "9e2234bb7cd8dff1285bc3295f4eb4ab8ea8d062",
    "login": "d39757b3bf257059cbaa0c2f786b49f954838c07",
    "datetime": "2023-10-25T06:41:24+02:00",
    "url": "https://nouveau.europresse.com:443/Pdf/ImageList?docName=pdf%C2%B720231025%C2%B7NIC_P%C2%B71",
    "status": "200",
    "size": "1243",
    "domain": "nouveau.europresse.com",
    "timestamp": 1698208884,
    "date": "2023-10-25",
    "log_id": "832ab027310350dd27189f78e22a4bc4093ac47c",
    "ezpaarse_version": "3.9.2",
    "ezpaarse_date": "2023-09-25",
    "middlewares_version": "1df4e1f",
    "middlewares_date": "2023-07-26",
    "platforms_version": "70ae7649",
    "platforms_date": "2023-09-22",
    "middlewares": "filter, parser, deduplicator, istex, crossref, sudoc, hal, enhancer, geolocalizer, cut, on-campus-counter, qualifier, anonymizer",
    "robot": "no",
    "platform": "europresse",
    "platform_name": "Europresse",
    "publisher_name": "CEDROM-SNi",
    "rtype": "ARTICLE",
    "mime": "PDF",
    "unitid": "pdf·20231025·NIC_P·1",
    "geoip-host": "86.229.32.166",
    "geoip-country": "FR",
    "geoip-region": "COR",
    "geoip-city": "Bastia",
    "geoip-latitude": "42.7028",
    "geoip-longitude": "9.45",
    "geoip-coordinates": "[42.7028,9.45]",
    "on_campus": "N"
  }
}