{
  "general": {
    "ezPAARSE-version": "ezpaarse 3.9.2",
    "Job-ID": "210741e0-f67e-11ee-bb32-0bf4b1458acc",
    "Job-Date": "2024-04-09T16:33:27+02:00",
    "Job-Done": true,
    "result-file-ecs": "http://localhost:59599/210741e0-f67e-11ee-bb32-0bf4b1458acc",
    "predefined-settings": false,
    "URL-Traces": "http://localhost:59599/210741e0-f67e-11ee-bb32-0bf4b1458acc/job-traces.log",
    "URL-Report": "http://localhost:59599/210741e0-f67e-11ee-bb32-0bf4b1458acc/job-report.json",
    "nb-ecs": 416,
    "nb-denied-ecs": 0,
    "nb-lines-input": 16798,
    "Rejection-Rate": "96.05 %",
    "Job-Duration": "12 s ",
    "process-speed": "1397 lignes/s",
    "client-user-agent": "axios/1.5.1",
    "ecs-speed": "34 ec/s",
    "git-branch": "HEAD",
    "git-tag": "3.9.2",
    "git-last-commit": "37e2aee2c8b8c87b53fe581233186a19cea2a3a7",
    "git-date": "2023-09-25",
    "input-format-proxy": "ezproxy",
    "input-format-literal": "%h %l %u %t \"%r\" %s %b",
    "input-format-regex": "/^([a-zA-Z0-9.\\-:]+(?:, ?[a-zA-Z0-9.\\-:]+)*) ([a-zA-Z0-9\\-]+) ([a-zA-Z0-9@.\\-_%,=]+) \\[([^\\]]+)\\] \"[A-Z]+ ([^ ]+) [^ ]+\" ([0-9]+) ([0-9]+)$/",
    "middlewares-version": "1df4e1f",
    "middlewares-date": "2023-07-26",
    "platforms-version": "70ae7649",
    "platforms-date": "2023-09-22",
    "middlewares": "filter, parser, deduplicator, istex, crossref, sudoc, hal, enhancer, geolocalizer, cut, on-campus-counter, qualifier, anonymizer",
    "crossref-queries": 2,
    "crossref-fails": 0,
    "crossref-invalid-dois": 0,
    "crossref-min-response-time": 2957,
    "crossref-max-response-time": 6094,
    "geolocalization": "",
    "on-campus-accesses": 0,
    "off-campus-accesses": 429,
    "url-denied-ecs": "http://localhost:59599/210741e0-f67e-11ee-bb32-0bf4b1458acc/denied-ecs.csv",
    "input-first-line": "193.240.184.99 - - [24/Mar/2024:00:04:22 -0400] \"GET https://udcpp.idm.oclc.org:8443/public/admin.htm HTTP/1.1\" 200 0"
  },
  "rejets": {
    "nb-lines-ignored": 6160,
    "nb-lines-duplicate-ecs": 17,
    "nb-lines-ignored-domains": 0,
    "nb-lines-unknown-domains": 1416,
    "nb-lines-unknown-formats": 0,
    "nb-lines-unqualified-ecs": 8785,
    "nb-lines-unordered-ecs": 0,
    "nb-lines-ignored-hosts": 0,
    "nb-lines-robots-ecs": 4,
    "nb-lines-unknown-errors": 0
  },
  "stats": {
    "platforms": 10,
    "mime-PDF": 151,
    "mime-HTML": 246,
    "platform-europresse": 238,
    "rtype-ARTICLE": 234,
    "platform-cairn": 54,
    "rtype-TOC": 9,
    "platform-lamyline": 7,
    "rtype-SEARCH": 55,
    "platform-lextenso": 22,
    "rtype-JURISPRUDENCE": 13,
    "rtype-BOOK_SECTION": 35,
    "platform-elnet": 18,
    "mime-MISC": 19,
    "platform-dalloz": 63,
    "platform-ebscohost": 4,
    "rtype-RECORD_VIEW": 3,
    "platform-universalis": 3,
    "rtype-ENCYCLOPAEDIA_ENTRY": 2,
    "rtype-IMAGE": 1,
    "rtype-FORMULES": 1,
    "platform-oej": 4,
    "platform-sd": 3
  },
  "alerts": {
    "active-alerts": "unknown-domains"
  },
  "dedoublonnage": {
    "activated": true,
    "strategy": "CLI",
    "fieldname-C": "session",
    "fieldname-L": "login",
    "fieldname-I": "host",
    "window-misc": 30,
    "window-html": 10,
    "window-pdf": 30
  },
  "first_event": {
    "host": "af6f0fd7f45d3258504bba532d076a303c237e30",
    "login": "daff9e95844c1d02ac004c9fd6efcc9eee736279",
    "datetime": "2024-03-24T05:37:59+01:00",
    "url": "https://nouveau.europresse.com:443/Pdf/ImageList?docName=pdf%C2%B720240324%C2%B7NIC_P%C2%B71",
    "status": "200",
    "size": "1492",
    "domain": "nouveau.europresse.com",
    "timestamp": 1711255079,
    "date": "2024-03-24",
    "log_id": "ea852f9408ac79128e93660a7611cde52332d18a",
    "ezpaarse_version": "3.9.2",
    "ezpaarse_date": "2023-09-25",
    "middlewares_version": "1df4e1f",
    "middlewares_date": "2023-07-26",
    "platforms_version": "70ae7649",
    "platforms_date": "2023-09-22",
    "middlewares": "filter, parser, deduplicator, istex, crossref, sudoc, hal, enhancer, geolocalizer, cut, on-campus-counter, qualifier, anonymizer",
    "robot": "no",
    "platform": "europresse",
    "platform_name": "Europresse",
    "publisher_name": "CEDROM-SNi",
    "rtype": "ARTICLE",
    "mime": "PDF",
    "unitid": "pdf·20240324·NIC_P·1",
    "geoip-host": "86.229.32.166",
    "geoip-country": "FR",
    "geoip-region": "COR",
    "geoip-city": "Bastia",
    "geoip-latitude": "42.7028",
    "geoip-longitude": "9.45",
    "geoip-coordinates": "[42.7028,9.45]",
    "on_campus": "N"
  }
}