{
  "general": {
    "ezPAARSE-version": "ezpaarse 3.9.2",
    "Job-ID": "41110250-f67e-11ee-bb32-0bf4b1458acc",
    "Job-Date": "2024-04-09T16:34:21+02:00",
    "Job-Done": true,
    "result-file-ecs": "http://localhost:59599/41110250-f67e-11ee-bb32-0bf4b1458acc",
    "predefined-settings": false,
    "URL-Traces": "http://localhost:59599/41110250-f67e-11ee-bb32-0bf4b1458acc/job-traces.log",
    "URL-Report": "http://localhost:59599/41110250-f67e-11ee-bb32-0bf4b1458acc/job-report.json",
    "nb-ecs": 1017,
    "nb-denied-ecs": 0,
    "nb-lines-input": 49248,
    "Rejection-Rate": "96.63 %",
    "Job-Duration": "14 s ",
    "process-speed": "3391 lignes/s",
    "client-user-agent": "axios/1.5.1",
    "ecs-speed": "70 ec/s",
    "git-branch": "HEAD",
    "git-tag": "3.9.2",
    "git-last-commit": "37e2aee2c8b8c87b53fe581233186a19cea2a3a7",
    "git-date": "2023-09-25",
    "input-format-proxy": "ezproxy",
    "input-format-literal": "%h %l %u %t \"%r\" %s %b",
    "input-format-regex": "/^([a-zA-Z0-9.\\-:]+(?:, ?[a-zA-Z0-9.\\-:]+)*) ([a-zA-Z0-9\\-]+) ([a-zA-Z0-9@.\\-_%,=]+) \\[([^\\]]+)\\] \"[A-Z]+ ([^ ]+) [^ ]+\" ([0-9]+) ([0-9]+)$/",
    "middlewares-version": "1df4e1f",
    "middlewares-date": "2023-07-26",
    "platforms-version": "70ae7649",
    "platforms-date": "2023-09-22",
    "middlewares": "filter, parser, deduplicator, istex, crossref, sudoc, hal, enhancer, geolocalizer, cut, on-campus-counter, qualifier, anonymizer",
    "crossref-queries": 2,
    "crossref-fails": 0,
    "crossref-invalid-dois": 0,
    "crossref-min-response-time": 3017,
    "crossref-max-response-time": 3556,
    "geolocalization": "",
    "on-campus-accesses": 0,
    "off-campus-accesses": 1186,
    "url-denied-ecs": "http://localhost:59599/41110250-f67e-11ee-bb32-0bf4b1458acc/denied-ecs.csv",
    "input-first-line": "46.193.64.212 - pvrBCo0eczMg9z0 [28/Mar/2024:00:00:15 -0400] \"GET https://www.dalloz.fr:443/api/session/tick?_=1711598414697 HTTP/1.1\" 200 0"
  },
  "rejets": {
    "nb-lines-ignored": 18192,
    "nb-lines-duplicate-ecs": 28,
    "nb-lines-ignored-domains": 26,
    "nb-lines-unknown-domains": 2061,
    "nb-lines-unknown-formats": 6,
    "nb-lines-unqualified-ecs": 27914,
    "nb-lines-unordered-ecs": 0,
    "nb-lines-ignored-hosts": 0,
    "nb-lines-robots-ecs": 4,
    "nb-lines-unknown-errors": 0
  },
  "stats": {
    "platforms": 13,
    "mime-PDF": 461,
    "mime-HTML": 535,
    "platform-europresse": 550,
    "rtype-ARTICLE": 593,
    "rtype-SEARCH": 79,
    "platform-sd": 13,
    "platform-dalloz": 228,
    "platform-lamyline": 47,
    "platform-cairn": 103,
    "rtype-BOOK_SECTION": 49,
    "rtype-TOC": 40,
    "platform-lextenso": 21,
    "platform-elnet": 21,
    "mime-MISC": 21,
    "platform-strada": 1,
    "platform-ebscohost": 26,
    "rtype-RECORD_VIEW": 17,
    "platform-wiley": 1,
    "rtype-JURISPRUDENCE": 9,
    "platform-rn": 2,
    "rtype-PREVIEW": 2,
    "platform-dalloz-revues": 3,
    "platform-numilog": 1
  },
  "alerts": {
    "active-alerts": "unknown-domains"
  },
  "dedoublonnage": {
    "activated": true,
    "strategy": "CLI",
    "fieldname-C": "session",
    "fieldname-L": "login",
    "fieldname-I": "host",
    "window-misc": 30,
    "window-html": 10,
    "window-pdf": 30
  },
  "first_event": {
    "host": "76e34543fc353dca33157ad1229518a74e751f11",
    "login": "63ee6feac21e685e58f1dce53dd79598d2dae0d0",
    "datetime": "2024-03-28T06:42:59+01:00",
    "url": "https://nouveau.europresse.com:443/Pdf/ImageList?docName=pdf%C2%B720240328%C2%B7NIC_P%C2%B71",
    "status": "200",
    "size": "1492",
    "domain": "nouveau.europresse.com",
    "timestamp": 1711604579,
    "date": "2024-03-28",
    "log_id": "9846d5ec29f4675fc55745efe981ea5af3e833ff",
    "ezpaarse_version": "3.9.2",
    "ezpaarse_date": "2023-09-25",
    "middlewares_version": "1df4e1f",
    "middlewares_date": "2023-07-26",
    "platforms_version": "70ae7649",
    "platforms_date": "2023-09-22",
    "middlewares": "filter, parser, deduplicator, istex, crossref, sudoc, hal, enhancer, geolocalizer, cut, on-campus-counter, qualifier, anonymizer",
    "robot": "no",
    "platform": "europresse",
    "platform_name": "Europresse",
    "publisher_name": "CEDROM-SNi",
    "rtype": "ARTICLE",
    "mime": "PDF",
    "unitid": "pdf·20240328·NIC_P·1",
    "geoip-host": "90.73.112.84",
    "geoip-country": "FR",
    "geoip-region": "PAC",
    "geoip-city": "Marseille",
    "geoip-latitude": "43.2966",
    "geoip-longitude": "5.3703",
    "geoip-coordinates": "[43.2966,5.3703]",
    "on_campus": "N"
  }
}